LICENSE.md
MANIFEST.in
README.md
requirements.txt
setup.py
mercury_base/__init__.py
mercury_base/utils.py
mercury_base.egg-info/PKG-INFO
mercury_base.egg-info/SOURCES.txt
mercury_base.egg-info/dependency_links.txt
mercury_base.egg-info/not-zip-safe
mercury_base.egg-info/requires.txt
mercury_base.egg-info/top_level.txt
mercury_base/mercury_v1/__init__.py
mercury_base/mercury_v1/commands.py
mercury_base/mercury_v2/__init__.py
mercury_base/mercury_v2/commands.py