Metadata-Version: 2.1
Name: mercury-base
Version: 1.5
Summary: Toolkit for communicating with Incotex Mercury meters via RS485/CAN bus
Home-page: https://github.com/webtoucher/mercury-base
Author: Alexey Kuznetsov
Author-email: mirakuru@webtoucher.ru
License: BSD-3-Clause
Classifier: Development Status :: 5 - Production/Stable
Classifier: Intended Audience :: Developers
Classifier: Topic :: Terminals :: Serial
Classifier: License :: OSI Approved :: BSD License
Classifier: Programming Language :: Python :: 3
Classifier: Operating System :: Unix
License-File: LICENSE.md
